README.md
setup.cfg
setup.py
AN_DiscordBot.egg-info/PKG-INFO
AN_DiscordBot.egg-info/SOURCES.txt
AN_DiscordBot.egg-info/dependency_links.txt
AN_DiscordBot.egg-info/entry_points.txt
AN_DiscordBot.egg-info/requires.txt
AN_DiscordBot.egg-info/top_level.txt
anbot/__init__.py
anbot/__main__.py
anbot/launcher.py
anbot/logging.py
anbot/meta.py
anbot/setup.py
anbot/cogs/__init__.py
anbot/core/__init__.py
anbot/core/bot.py
anbot/core/checks.py
anbot/core/cli.py
anbot/core/cog_manager.py
anbot/core/config.py
anbot/core/core_commands.py
anbot/core/data_manager.py
anbot/core/errors.py
anbot/core/events.py
anbot/core/global_checks.py
anbot/core/help_formatter.py
anbot/core/i18n.py
anbot/core/json_io.py
anbot/core/modlog.py
anbot/core/rpc.py
anbot/core/sentry.py
anbot/core/commands/__init__.py
anbot/core/commands/commands.py
anbot/core/commands/context.py
anbot/core/commands/converter.py
anbot/core/commands/errors.py
anbot/core/commands/requires.py
anbot/core/drivers/__init__.py
anbot/core/drivers/red_base.py
anbot/core/drivers/red_json.py
anbot/core/drivers/red_mongo.py
anbot/core/locales/ar-SA.po
anbot/core/locales/bg-BG.po
anbot/core/locales/da-DK.po
anbot/core/locales/de-DE.po
anbot/core/locales/debugging.po
anbot/core/locales/el-GR.po
anbot/core/locales/en-PT.po
anbot/core/locales/es-ES.po
anbot/core/locales/fi-FI.po
anbot/core/locales/fr-FR.po
anbot/core/locales/hu-HU.po
anbot/core/locales/id-ID.po
anbot/core/locales/it-IT.po
anbot/core/locales/ja-JP.po
anbot/core/locales/ko-KR.po
anbot/core/locales/lol-US.po
anbot/core/locales/nl-NL.po
anbot/core/locales/no-NO.po
anbot/core/locales/pl-PL.po
anbot/core/locales/pt-BR.po
anbot/core/locales/pt-PT.po
anbot/core/locales/ru-RU.po
anbot/core/locales/sv-SE.po
anbot/core/locales/zh-CN.po
anbot/core/utils/__init__.py
anbot/core/utils/antispam.py
anbot/core/utils/caching.py
anbot/core/utils/chat_formatting.py
anbot/core/utils/common_filters.py
anbot/core/utils/data_converter.py
anbot/core/utils/embed.py
anbot/core/utils/menus.py
anbot/core/utils/mod.py
anbot/core/utils/predicates.py
anbot/core/utils/tunnel.py